Workbook

Sheet 使用说明
B1: 中山店铺 · 管理账本 使用说明
B3: 这本账替代手写流水账:每天下午花30分钟录入,月底应收、库存、利润自动算出来。
B5: 【一天怎么用】
B6: 1. 晚上接单后 → 把订单一条条记进【订单登记】(一个品种一行,同一单用同一个订单号)
B7: 2. 清晨市场采购回来 → 记【采购记录】(照着收据抄)
B8: 3. 下午回执收回来 → 记【送货回执登记】;收到的每一笔钱(包括现结当场收的)记【收款记录】
B9: 4. 想看谁欠多少钱 → 打开【应收对账】,自动算好;想看货还剩多少 → 打开【库存】
B10: 5. 月底看【月度汇总】,费用那几格手填,净利自动出
B12: 【颜色和规矩】
B13: · 浅黄色的行是示例,照着格式填,看懂后可整行删除(库存表黄色期初数改成自己盘点的数)
B14: · 表头是深蓝色;凡是“金额、期末应收、当前库存”这类自动算的格子,里面是公式,不要手改
B15: · 品名和规格必须与【商品目录】写得一字不差(建议复制粘贴),否则库存对不上账
... B28: 配套纸质单据版式见仓库 templates/ 目录;整套用法见 docs/ 目录八篇方案。

Sheet 商品目录
A1: 编码 | B1: 品名 | C1: 规格 | D1: 单位 | E1: 参考进价(元) | F1: 销售单价(元) | G1: 主供应商 | H1: 保质期(月) | I1: 安全库存 | J1: 备注
A2: TW-001 | B2: 黄豆酱油 | C2: 10L/桶 | D2: 桶 | E2: 45 | F2: 55 | G2: 王记调味(市场A区12号) | H2: 18 | I2: 10 | J2: 示例行,可删
A3: TW-002 | B3: 老陈醋 | C3: 420ml×15瓶/件 | D3: 件 | E3: 28 | F3: 35 | G3: 王记调味(市场A区12号) | H3: 24 | I3: 8 | J3: 示例行,可删
A4: TW-003 | B4: 花椒 | C4: 500g/袋 | D4: 袋 | E4: 22 | F4: 30 | G4: 李记干货(市场B区3号) | H4: 12 | I4: 5 | J4: 示例行,可删
A5: LY-001 | B5: 大豆油 | C5: 20L/桶 | D5: 桶 | E5: 115 | F5: 130 | G5: 张记粮油(市场C区1号) | H5: 12 | I5: 6 | J5: 示例行,可删
A6: LY-002 | B6: 高筋面粉 | C6: 25kg/袋 | D6: 袋 | E6: 82 | F6: 95 | G6: 张记粮油(市场C区1号) | H6: 6 | I6: 10 | J6: 示例行,可删

Sheet 客户档案
A1: 客户编号 | B1: 店名 | C1: 分级 | D1: 老板姓名 | E1: 电话 | F1: 微信备注名 | G1: 店铺地址 | H1: 收货时间要求 | I1: 指定收货人 | J1: 结算方式 | K1: 信用额度(元) | L1: 常用品 | M1: 备注
A2: KH-001 | B2: 老王饺子馆 | C2: B | D2: 王建国 | E2: 13800005678 | F2: B-老王饺子馆-王老板 | G2: 中山路45号 | H2: 上午10点前 | I2: 王建国/小李 | J2: 半月结 | K2: 3000 | L2: 酱油、醋、面粉 | M2: 示例行,可删
A3: KH-002 | B3: 学苑食堂3号档口 | C3: A | D3: 刘敏 | E3: 13900001234 | F3: A-学苑食堂3档-刘姐 | G3: 大学城食堂一楼 | H3: 上午9点前 | I3: 刘敏 | J3: 月结 | K3: 8000 | L3: 大豆油、面粉、花椒 | M3: 示例行,可删
A4: KH-003 | B4: 红星烧烤 | C4: C | D4: 赵磊 | E4: 13700009999 | F4: C-红星烧烤-赵老板 | G4: 建设街12号 | H4: 下午4点前 | I4: 赵磊 | J4: 现结 | K4: 0 | L4: 花椒、大豆油 | M4: 示例行,可删

Sheet 订单登记
A1: 日期 | B1: 订单号 | C1: 客户 | D1: 品名 | E1: 规格 | F1: 数量 | G1: 单位 | H1: 单价(元) | I1: 金额(元)自动 | J1: 要求送达时间 | K1: 备注 | L1: 状态
A2: 2026-07-31 | B2: DD20260731-01 | C2: 老王饺子馆 | D2: 黄豆酱油 | E2: 10L/桶 | F2: 2 | G2: 桶 | H2: 55 | I2: =IF(F2="","",F2*H2) -> 110 | J2: 上午10点前 | K2: 示例行,可删 | L2: 已签收
A3: 2026-07-31 | B3: DD20260731-01 | C3: 老王饺子馆 | D3: 老陈醋 | E3: 420ml×15瓶/件 | F3: 1 | G3: 件 | H3: 35 | I3: =IF(F3="","",F3*H3) -> 35 | J3: 上午10点前 | K3: 示例行,可删 | L3: 已签收
A4: 2026-07-31 | B4: DD20260731-02 | C4: 学苑食堂3号档口 | D4: 大豆油 | E4: 20L/桶 | F4: 3 | G4: 桶 | H4: 130 | I4: =IF(F4="","",F4*H4) -> 390 | J4: 上午9点前 | K4: 示例行,可删 | L4: 已签收
I5: =IF(F5="","",F5*H5)
I6: =IF(F6="","",F6*H6)
I7: =IF(F7="","",F7*H7)
I8: =IF(F8="","",F8*H8)
I9: =IF(F9="","",F9*H9)
I10: =IF(F10="","",F10*H10)
I11: =IF(F11="","",F11*H11)
I12: =IF(F12="","",F12*H12)
I13: =IF(F13="","",F13*H13)
I14: =IF(F14="","",F14*H14)
I15: =IF(F15="","",F15*H15)
I16: =IF(F16="","",F16*H16)
... I500: =IF(F500="","",F500*H500)

Sheet 采购记录
A1: 日期 | B1: 品名 | C1: 规格 | D1: 数量 | E1: 单位 | F1: 单价(元) | G1: 金额(元)自动 | H1: 供应商 | I1: 有无票据 | J1: 备注
A2: 2026-07-31 | B2: 黄豆酱油 | C2: 10L/桶 | D2: 4 | E2: 桶 | F2: 45 | G2: =IF(D2="","",D2*F2) -> 180 | H2: 王记调味(市场A区12号) | I2: 有 | J2: 示例行,可删
A3: 2026-07-31 | B3: 大豆油 | C3: 20L/桶 | D3: 3 | E3: 桶 | F3: 115 | G3: =IF(D3="","",D3*F3) -> 345 | H3: 张记粮油(市场C区1号) | I3: 有 | J3: 示例行,可删
G4: =IF(D4="","",D4*F4)
G5: =IF(D5="","",D5*F5)
G6: =IF(D6="","",D6*F6)
G7: =IF(D7="","",D7*F7)
G8: =IF(D8="","",D8*F8)
G9: =IF(D9="","",D9*F9)
G10: =IF(D10="","",D10*F10)
G11: =IF(D11="","",D11*F11)
G12: =IF(D12="","",D12*F12)
G13: =IF(D13="","",D13*F13)
G14: =IF(D14="","",D14*F14)
G15: =IF(D15="","",D15*F15)
... G500: =IF(D500="","",D500*F500)

Sheet 送货回执登记
A1: 日期 | B1: 回执单号 | C1: 客户 | D1: 金额(元) | E1: 结算方式 | F1: 是否签收 | G1: 回执是否收回 | H1: 收货人 | I1: 备注
A2: 2026-07-31 | B2: HZ20260731-01 | C2: 老王饺子馆 | D2: 145 | E2: 半月结 | F2: 是 | G2: 是 | H2: 小李(员工) | I2: 示例行,可删
A3: 2026-07-31 | B3: HZ20260731-02 | C3: 学苑食堂3号档口 | D3: 390 | E3: 月结 | F3: 是 | G3: 是 | H3: 刘敏 | I3: 示例行,可删

Sheet 收款记录
A1: 日期 | B1: 客户 | C1: 金额(元) | D1: 收款方式 | E1: 备注
A2: 2026-07-31 | B2: 老王饺子馆 | C2: 100 | D2: 微信 | E2: 示例行,可删(还上期部分欠款)

Sheet 应收对账
A1: 客户(自动) | B1: 期初欠款(元)手填 | C1: 本期送货(元)自动 | D1: 本期已收(元)自动 | E1: 期末应收(元)自动 | F1: 信用额度(元)自动 | G1: 提醒
A2: =IF(客户档案!B2="","",客户档案!B2) -> 老王饺子馆 | B2: 0 | C2: =IF(A2="","",SUMIF(送货回执登记!$C$2:$C$500,A2,送货回执登记!$D$2:$D$500)) -> 145 | D2: =IF(A2="","",SUMIF(收款记录!$B$2:$B$500,A2,收款记录!$C$2:$C$500)) -> 100 | E2: =IF(A2="","",N(B2)+C2-D2) -> 45 | F2: =IF(A2="","",IFERROR(INDEX(客户档案!$K$2:$K$300,MATCH(A2,客户档案!$B$2:$B$300,0)),"")) -> 3000 | G2: =IF(A2="","",IF(ISNUMBER(F2),IF(AND(F2>0,E2>F2),"超额!先收款再供货",""),""))
A3: =IF(客户档案!B3="","",客户档案!B3) -> 学苑食堂3号档口 | B3: 0 | C3: =IF(A3="","",SUMIF(送货回执登记!$C$2:$C$500,A3,送货回执登记!$D$2:$D$500)) -> 390 | D3: =IF(A3="","",SUMIF(收款记录!$B$2:$B$500,A3,收款记录!$C$2:$C$500)) -> 0 | E3: =IF(A3="","",N(B3)+C3-D3) -> 390 | F3: =IF(A3="","",IFERROR(INDEX(客户档案!$K$2:$K$300,MATCH(A3,客户档案!$B$2:$B$300,0)),"")) -> 8000 | G3: =IF(A3="","",IF(ISNUMBER(F3),IF(AND(F3>0,E3>F3),"超额!先收款再供货",""),""))
A4: =IF(客户档案!B4="","",客户档案!B4) -> 红星烧烤 | B4: 0 | C4: =IF(A4="","",SUMIF(送货回执登记!$C$2:$C$500,A4,送货回执登记!$D$2:$D$500)) -> 0 | D4: =IF(A4="","",SUMIF(收款记录!$B$2:$B$500,A4,收款记录!$C$2:$C$500)) -> 0 | E4: =IF(A4="","",N(B4)+C4-D4) -> 0 | F4: =IF(A4="","",IFERROR(INDEX(客户档案!$K$2:$K$300,MATCH(A4,客户档案!$B$2:$B$300,0)),"")) -> 0 | G4: =IF(A4="","",IF(ISNUMBER(F4),IF(AND(F4>0,E4>F4),"超额!先收款再供货",""),""))
A5: =IF(客户档案!B5="","",客户档案!B5) | C5: =IF(A5="","",SUMIF(送货回执登记!$C$2:$C$500,A5,送货回执登记!$D$2:$D$500)) | D5: =IF(A5="","",SUMIF(收款记录!$B$2:$B$500,A5,收款记录!$C$2:$C$500)) | E5: =IF(A5="","",N(B5)+C5-D5) | F5: =IF(A5="","",IFERROR(INDEX(客户档案!$K$2:$K$300,MATCH(A5,客户档案!$B$2:$B$300,0)),"")) | G5: =IF(A5="","",IF(ISNUMBER(F5),IF(AND(F5>0,E5>F5),"超额!先收款再供货",""),""))
A6: =IF(客户档案!B6="","",客户档案!B6) | C6: =IF(A6="","",SUMIF(送货回执登记!$C$2:$C$500,A6,送货回执登记!$D$2:$D$500)) | D6: =IF(A6="","",SUMIF(收款记录!$B$2:$B$500,A6,收款记录!$C$2:$C$500)) | E6: =IF(A6="","",N(B6)+C6-D6) | F6: =IF(A6="","",IFERROR(INDEX(客户档案!$K$2:$K$300,MATCH(A6,客户档案!$B$2:$B$300,0)),"")) | G6: =IF(A6="","",IF(ISNUMBER(F6),IF(AND(F6>0,E6>F6),"超额!先收款再供货",""),""))
A7: =IF(客户档案!B7="","",客户档案!B7) | C7: =IF(A7="","",SUMIF(送货回执登记!$C$2:$C$500,A7,送货回执登记!$D$2:$D$500)) | D7: =IF(A7="","",SUMIF(收款记录!$B$2:$B$500,A7,收款记录!$C$2:$C$500)) | E7: =IF(A7="","",N(B7)+C7-D7) | F7: =IF(A7="","",IFERROR(INDEX(客户档案!$K$2:$K$300,MATCH(A7,客户档案!$B$2:$B$300,0)),"")) | G7: =IF(A7="","",IF(ISNUMBER(F7),IF(AND(F7>0,E7>F7),"超额!先收款再供货",""),""))
A8: =IF(客户档案!B8="","",客户档案!B8) | C8: =IF(A8="","",SUMIF(送货回执登记!$C$2:$C$500,A8,送货回执登记!$D$2:$D$500)) | D8: =IF(A8="","",SUMIF(收款记录!$B$2:$B$500,A8,收款记录!$C$2:$C$500)) | E8: =IF(A8="","",N(B8)+C8-D8) | F8: =IF(A8="","",IFERROR(INDEX(客户档案!$K$2:$K$300,MATCH(A8,客户档案!$B$2:$B$300,0)),"")) | G8: =IF(A8="","",IF(ISNUMBER(F8),IF(AND(F8>0,E8>F8),"超额!先收款再供货",""),""))
A9: =IF(客户档案!B9="","",客户档案!B9) | C9: =IF(A9="","",SUMIF(送货回执登记!$C$2:$C$500,A9,送货回执登记!$D$2:$D$500)) | D9: =IF(A9="","",SUMIF(收款记录!$B$2:$B$500,A9,收款记录!$C$2:$C$500)) | E9: =IF(A9="","",N(B9)+C9-D9) | F9: =IF(A9="","",IFERROR(INDEX(客户档案!$K$2:$K$300,MATCH(A9,客户档案!$B$2:$B$300,0)),"")) | G9: =IF(A9="","",IF(ISNUMBER(F9),IF(AND(F9>0,E9>F9),"超额!先收款再供货",""),""))
A10: =IF(客户档案!B10="","",客户档案!B10) | C10: =IF(A10="","",SUMIF(送货回执登记!$C$2:$C$500,A10,送货回执登记!$D$2:$D$500)) | D10: =IF(A10="","",SUMIF(收款记录!$B$2:$B$500,A10,收款记录!$C$2:$C$500)) | E10: =IF(A10="","",N(B10)+C10-D10) | F10: =IF(A10="","",IFERROR(INDEX(客户档案!$K$2:$K$300,MATCH(A10,客户档案!$B$2:$B$300,0)),"")) | G10: =IF(A10="","",IF(ISNUMBER(F10),IF(AND(F10>0,E10>F10),"超额!先收款再供货",""),""))
A11: =IF(客户档案!B11="","",客户档案!B11) | C11: =IF(A11="","",SUMIF(送货回执登记!$C$2:$C$500,A11,送货回执登记!$D$2:$D$500)) | D11: =IF(A11="","",SUMIF(收款记录!$B$2:$B$500,A11,收款记录!$C$2:$C$500)) | E11: =IF(A11="","",N(B11)+C11-D11) | F11: =IF(A11="","",IFERROR(INDEX(客户档案!$K$2:$K$300,MATCH(A11,客户档案!$B$2:$B$300,0)),"")) | G11: =IF(A11="","",IF(ISNUMBER(F11),IF(AND(F11>0,E11>F11),"超额!先收款再供货",""),""))
A12: =IF(客户档案!B12="","",客户档案!B12) | C12: =IF(A12="","",SUMIF(送货回执登记!$C$2:$C$500,A12,送货回执登记!$D$2:$D$500)) | D12: =IF(A12="","",SUMIF(收款记录!$B$2:$B$500,A12,收款记录!$C$2:$C$500)) | E12: =IF(A12="","",N(B12)+C12-D12) | F12: =IF(A12="","",IFERROR(INDEX(客户档案!$K$2:$K$300,MATCH(A12,客户档案!$B$2:$B$300,0)),"")) | G12: =IF(A12="","",IF(ISNUMBER(F12),IF(AND(F12>0,E12>F12),"超额!先收款再供货",""),""))
A13: =IF(客户档案!B13="","",客户档案!B13) | C13: =IF(A13="","",SUMIF(送货回执登记!$C$2:$C$500,A13,送货回执登记!$D$2:$D$500)) | D13: =IF(A13="","",SUMIF(收款记录!$B$2:$B$500,A13,收款记录!$C$2:$C$500)) | E13: =IF(A13="","",N(B13)+C13-D13) | F13: =IF(A13="","",IFERROR(INDEX(客户档案!$K$2:$K$300,MATCH(A13,客户档案!$B$2:$B$300,0)),"")) | G13: =IF(A13="","",IF(ISNUMBER(F13),IF(AND(F13>0,E13>F13),"超额!先收款再供货",""),""))
A14: =IF(客户档案!B14="","",客户档案!B14) | C14: =IF(A14="","",SUMIF(送货回执登记!$C$2:$C$500,A14,送货回执登记!$D$2:$D$500)) | D14: =IF(A14="","",SUMIF(收款记录!$B$2:$B$500,A14,收款记录!$C$2:$C$500)) | E14: =IF(A14="","",N(B14)+C14-D14) | F14: =IF(A14="","",IFERROR(INDEX(客户档案!$K$2:$K$300,MATCH(A14,客户档案!$B$2:$B$300,0)),"")) | G14: =IF(A14="","",IF(ISNUMBER(F14),IF(AND(F14>0,E14>F14),"超额!先收款再供货",""),""))
A15: =IF(客户档案!B15="","",客户档案!B15) | C15: =IF(A15="","",SUMIF(送货回执登记!$C$2:$C$500,A15,送货回执登记!$D$2:$D$500)) | D15: =IF(A15="","",SUMIF(收款记录!$B$2:$B$500,A15,收款记录!$C$2:$C$500)) | E15: =IF(A15="","",N(B15)+C15-D15) | F15: =IF(A15="","",IFERROR(INDEX(客户档案!$K$2:$K$300,MATCH(A15,客户档案!$B$2:$B$300,0)),"")) | G15: =IF(A15="","",IF(ISNUMBER(F15),IF(AND(F15>0,E15>F15),"超额!先收款再供货",""),""))
A16: =IF(客户档案!B16="","",客户档案!B16) | C16: =IF(A16="","",SUMIF(送货回执登记!$C$2:$C$500,A16,送货回执登记!$D$2:$D$500)) | D16: =IF(A16="","",SUMIF(收款记录!$B$2:$B$500,A16,收款记录!$C$2:$C$500)) | E16: =IF(A16="","",N(B16)+C16-D16) | F16: =IF(A16="","",IFERROR(INDEX(客户档案!$K$2:$K$300,MATCH(A16,客户档案!$B$2:$B$300,0)),"")) | G16: =IF(A16="","",IF(ISNUMBER(F16),IF(AND(F16>0,E16>F16),"超额!先收款再供货",""),""))
... A151: =IF(客户档案!B151="","",客户档案!B151) | C151: =IF(A151="","",SUMIF(送货回执登记!$C$2:$C$500,A151,送货回执登记!$D$2:$D$500)) | D151: =IF(A151="","",SUMIF(收款记录!$B$2:$B$500,A151,收款记录!$C$2:$C$500)) | E151: =IF(A151="","",N(B151)+C151-D151) | F151: =IF(A151="","",IFERROR(INDEX(客户档案!$K$2:$K$300,MATCH(A151,客户档案!$B$2:$B$300,0)),"")) | G151: =IF(A151="","",IF(ISNUMBER(F151),IF(AND(F151>0,E151>F151),"超额!先收款再供货",""),""))

Sheet 库存
A1: 品名(自动) | B1: 规格(自动) | C1: 单位(自动) | D1: 期初库存 手填 | E1: 本期采购入库(自动) | F1: 本期销售出库(自动) | G1: 当前库存(自动) | H1: 安全库存(自动) | I1: 补货提醒
A2: =IF(商品目录!B2="","",商品目录!B2) -> 黄豆酱油 | B2: =IF(A2="","",商品目录!C2) -> 10L/桶 | C2: =IF(A2="","",商品目录!D2) -> 桶 | D2: 5 | E2: =IF(A2="","",SUMIFS(采购记录!$D$2:$D$500,采购记录!$B$2:$B$500,A2,采购记录!$C$2:$C$500,B2)) -> 4 | F2: =IF(A2="","",SUMIFS(订单登记!$F$2:$F$500,订单登记!$D$2:$D$500,A2,订单登记!$E$2:$E$500,B2)) -> 2 | G2: =IF(A2="","",N(D2)+E2-F2) -> 7 | H2: =IF(A2="","",商品目录!I2) -> 10 | I2: =IF(A2="","",IF(ISNUMBER(H2),IF(G2<H2,"该补货",""),"")) -> 该补货
A3: =IF(商品目录!B3="","",商品目录!B3) -> 老陈醋 | B3: =IF(A3="","",商品目录!C3) -> 420ml×15瓶/件 | C3: =IF(A3="","",商品目录!D3) -> 件 | D3: 3 | E3: =IF(A3="","",SUMIFS(采购记录!$D$2:$D$500,采购记录!$B$2:$B$500,A3,采购记录!$C$2:$C$500,B3)) -> 0 | F3: =IF(A3="","",SUMIFS(订单登记!$F$2:$F$500,订单登记!$D$2:$D$500,A3,订单登记!$E$2:$E$500,B3)) -> 1 | G3: =IF(A3="","",N(D3)+E3-F3) -> 2 | H3: =IF(A3="","",商品目录!I3) -> 8 | I3: =IF(A3="","",IF(ISNUMBER(H3),IF(G3<H3,"该补货",""),"")) -> 该补货
A4: =IF(商品目录!B4="","",商品目录!B4) -> 花椒 | B4: =IF(A4="","",商品目录!C4) -> 500g/袋 | C4: =IF(A4="","",商品目录!D4) -> 袋 | D4: 2 | E4: =IF(A4="","",SUMIFS(采购记录!$D$2:$D$500,采购记录!$B$2:$B$500,A4,采购记录!$C$2:$C$500,B4)) -> 0 | F4: =IF(A4="","",SUMIFS(订单登记!$F$2:$F$500,订单登记!$D$2:$D$500,A4,订单登记!$E$2:$E$500,B4)) -> 0 | G4: =IF(A4="","",N(D4)+E4-F4) -> 2 | H4: =IF(A4="","",商品目录!I4) -> 5 | I4: =IF(A4="","",IF(ISNUMBER(H4),IF(G4<H4,"该补货",""),"")) -> 该补货
A5: =IF(商品目录!B5="","",商品目录!B5) -> 大豆油 | B5: =IF(A5="","",商品目录!C5) -> 20L/桶 | C5: =IF(A5="","",商品目录!D5) -> 桶 | D5: 2 | E5: =IF(A5="","",SUMIFS(采购记录!$D$2:$D$500,采购记录!$B$2:$B$500,A5,采购记录!$C$2:$C$500,B5)) -> 3 | F5: =IF(A5="","",SUMIFS(订单登记!$F$2:$F$500,订单登记!$D$2:$D$500,A5,订单登记!$E$2:$E$500,B5)) -> 3 | G5: =IF(A5="","",N(D5)+E5-F5) -> 2 | H5: =IF(A5="","",商品目录!I5) -> 6 | I5: =IF(A5="","",IF(ISNUMBER(H5),IF(G5<H5,"该补货",""),"")) -> 该补货
A6: =IF(商品目录!B6="","",商品目录!B6) -> 高筋面粉 | B6: =IF(A6="","",商品目录!C6) -> 25kg/袋 | C6: =IF(A6="","",商品目录!D6) -> 袋 | D6: 4 | E6: =IF(A6="","",SUMIFS(采购记录!$D$2:$D$500,采购记录!$B$2:$B$500,A6,采购记录!$C$2:$C$500,B6)) -> 0 | F6: =IF(A6="","",SUMIFS(订单登记!$F$2:$F$500,订单登记!$D$2:$D$500,A6,订单登记!$E$2:$E$500,B6)) -> 0 | G6: =IF(A6="","",N(D6)+E6-F6) -> 4 | H6: =IF(A6="","",商品目录!I6) -> 10 | I6: =IF(A6="","",IF(ISNUMBER(H6),IF(G6<H6,"该补货",""),"")) -> 该补货
A7: =IF(商品目录!B7="","",商品目录!B7) | B7: =IF(A7="","",商品目录!C7) | C7: =IF(A7="","",商品目录!D7) | E7: =IF(A7="","",SUMIFS(采购记录!$D$2:$D$500,采购记录!$B$2:$B$500,A7,采购记录!$C$2:$C$500,B7)) | F7: =IF(A7="","",SUMIFS(订单登记!$F$2:$F$500,订单登记!$D$2:$D$500,A7,订单登记!$E$2:$E$500,B7)) | G7: =IF(A7="","",N(D7)+E7-F7) | H7: =IF(A7="","",商品目录!I7) | I7: =IF(A7="","",IF(ISNUMBER(H7),IF(G7<H7,"该补货",""),""))
A8: =IF(商品目录!B8="","",商品目录!B8) | B8: =IF(A8="","",商品目录!C8) | C8: =IF(A8="","",商品目录!D8) | E8: =IF(A8="","",SUMIFS(采购记录!$D$2:$D$500,采购记录!$B$2:$B$500,A8,采购记录!$C$2:$C$500,B8)) | F8: =IF(A8="","",SUMIFS(订单登记!$F$2:$F$500,订单登记!$D$2:$D$500,A8,订单登记!$E$2:$E$500,B8)) | G8: =IF(A8="","",N(D8)+E8-F8) | H8: =IF(A8="","",商品目录!I8) | I8: =IF(A8="","",IF(ISNUMBER(H8),IF(G8<H8,"该补货",""),""))
A9: =IF(商品目录!B9="","",商品目录!B9) | B9: =IF(A9="","",商品目录!C9) | C9: =IF(A9="","",商品目录!D9) | E9: =IF(A9="","",SUMIFS(采购记录!$D$2:$D$500,采购记录!$B$2:$B$500,A9,采购记录!$C$2:$C$500,B9)) | F9: =IF(A9="","",SUMIFS(订单登记!$F$2:$F$500,订单登记!$D$2:$D$500,A9,订单登记!$E$2:$E$500,B9)) | G9: =IF(A9="","",N(D9)+E9-F9) | H9: =IF(A9="","",商品目录!I9) | I9: =IF(A9="","",IF(ISNUMBER(H9),IF(G9<H9,"该补货",""),""))
A10: =IF(商品目录!B10="","",商品目录!B10) | B10: =IF(A10="","",商品目录!C10) | C10: =IF(A10="","",商品目录!D10) | E10: =IF(A10="","",SUMIFS(采购记录!$D$2:$D$500,采购记录!$B$2:$B$500,A10,采购记录!$C$2:$C$500,B10)) | F10: =IF(A10="","",SUMIFS(订单登记!$F$2:$F$500,订单登记!$D$2:$D$500,A10,订单登记!$E$2:$E$500,B10)) | G10: =IF(A10="","",N(D10)+E10-F10) | H10: =IF(A10="","",商品目录!I10) | I10: =IF(A10="","",IF(ISNUMBER(H10),IF(G10<H10,"该补货",""),""))
A11: =IF(商品目录!B11="","",商品目录!B11) | B11: =IF(A11="","",商品目录!C11) | C11: =IF(A11="","",商品目录!D11) | E11: =IF(A11="","",SUMIFS(采购记录!$D$2:$D$500,采购记录!$B$2:$B$500,A11,采购记录!$C$2:$C$500,B11)) | F11: =IF(A11="","",SUMIFS(订单登记!$F$2:$F$500,订单登记!$D$2:$D$500,A11,订单登记!$E$2:$E$500,B11)) | G11: =IF(A11="","",N(D11)+E11-F11) | H11: =IF(A11="","",商品目录!I11) | I11: =IF(A11="","",IF(ISNUMBER(H11),IF(G11<H11,"该补货",""),""))
A12: =IF(商品目录!B12="","",商品目录!B12) | B12: =IF(A12="","",商品目录!C12) | C12: =IF(A12="","",商品目录!D12) | E12: =IF(A12="","",SUMIFS(采购记录!$D$2:$D$500,采购记录!$B$2:$B$500,A12,采购记录!$C$2:$C$500,B12)) | F12: =IF(A12="","",SUMIFS(订单登记!$F$2:$F$500,订单登记!$D$2:$D$500,A12,订单登记!$E$2:$E$500,B12)) | G12: =IF(A12="","",N(D12)+E12-F12) | H12: =IF(A12="","",商品目录!I12) | I12: =IF(A12="","",IF(ISNUMBER(H12),IF(G12<H12,"该补货",""),""))
A13: =IF(商品目录!B13="","",商品目录!B13) | B13: =IF(A13="","",商品目录!C13) | C13: =IF(A13="","",商品目录!D13) | E13: =IF(A13="","",SUMIFS(采购记录!$D$2:$D$500,采购记录!$B$2:$B$500,A13,采购记录!$C$2:$C$500,B13)) | F13: =IF(A13="","",SUMIFS(订单登记!$F$2:$F$500,订单登记!$D$2:$D$500,A13,订单登记!$E$2:$E$500,B13)) | G13: =IF(A13="","",N(D13)+E13-F13) | H13: =IF(A13="","",商品目录!I13) | I13: =IF(A13="","",IF(ISNUMBER(H13),IF(G13<H13,"该补货",""),""))
A14: =IF(商品目录!B14="","",商品目录!B14) | B14: =IF(A14="","",商品目录!C14) | C14: =IF(A14="","",商品目录!D14) | E14: =IF(A14="","",SUMIFS(采购记录!$D$2:$D$500,采购记录!$B$2:$B$500,A14,采购记录!$C$2:$C$500,B14)) | F14: =IF(A14="","",SUMIFS(订单登记!$F$2:$F$500,订单登记!$D$2:$D$500,A14,订单登记!$E$2:$E$500,B14)) | G14: =IF(A14="","",N(D14)+E14-F14) | H14: =IF(A14="","",商品目录!I14) | I14: =IF(A14="","",IF(ISNUMBER(H14),IF(G14<H14,"该补货",""),""))
A15: =IF(商品目录!B15="","",商品目录!B15) | B15: =IF(A15="","",商品目录!C15) | C15: =IF(A15="","",商品目录!D15) | E15: =IF(A15="","",SUMIFS(采购记录!$D$2:$D$500,采购记录!$B$2:$B$500,A15,采购记录!$C$2:$C$500,B15)) | F15: =IF(A15="","",SUMIFS(订单登记!$F$2:$F$500,订单登记!$D$2:$D$500,A15,订单登记!$E$2:$E$500,B15)) | G15: =IF(A15="","",N(D15)+E15-F15) | H15: =IF(A15="","",商品目录!I15) | I15: =IF(A15="","",IF(ISNUMBER(H15),IF(G15<H15,"该补货",""),""))
A16: =IF(商品目录!B16="","",商品目录!B16) | B16: =IF(A16="","",商品目录!C16) | C16: =IF(A16="","",商品目录!D16) | E16: =IF(A16="","",SUMIFS(采购记录!$D$2:$D$500,采购记录!$B$2:$B$500,A16,采购记录!$C$2:$C$500,B16)) | F16: =IF(A16="","",SUMIFS(订单登记!$F$2:$F$500,订单登记!$D$2:$D$500,A16,订单登记!$E$2:$E$500,B16)) | G16: =IF(A16="","",N(D16)+E16-F16) | H16: =IF(A16="","",商品目录!I16) | I16: =IF(A16="","",IF(ISNUMBER(H16),IF(G16<H16,"该补货",""),""))
A17: =IF(商品目录!B17="","",商品目录!B17) | B17: =IF(A17="","",商品目录!C17) | C17: =IF(A17="","",商品目录!D17) | E17: =IF(A17="","",SUMIFS(采购记录!$D$2:$D$500,采购记录!$B$2:$B$500,A17,采购记录!$C$2:$C$500,B17)) | F17: =IF(A17="","",SUMIFS(订单登记!$F$2:$F$500,订单登记!$D$2:$D$500,A17,订单登记!$E$2:$E$500,B17)) | G17: =IF(A17="","",N(D17)+E17-F17) | H17: =IF(A17="","",商品目录!I17) | I17: =IF(A17="","",IF(ISNUMBER(H17),IF(G17<H17,"该补货",""),""))
A18: =IF(商品目录!B18="","",商品目录!B18) | B18: =IF(A18="","",商品目录!C18) | C18: =IF(A18="","",商品目录!D18) | E18: =IF(A18="","",SUMIFS(采购记录!$D$2:$D$500,采购记录!$B$2:$B$500,A18,采购记录!$C$2:$C$500,B18)) | F18: =IF(A18="","",SUMIFS(订单登记!$F$2:$F$500,订单登记!$D$2:$D$500,A18,订单登记!$E$2:$E$500,B18)) | G18: =IF(A18="","",N(D18)+E18-F18) | H18: =IF(A18="","",商品目录!I18) | I18: =IF(A18="","",IF(ISNUMBER(H18),IF(G18<H18,"该补货",""),""))
... A201: =IF(商品目录!B201="","",商品目录!B201) | B201: =IF(A201="","",商品目录!C201) | C201: =IF(A201="","",商品目录!D201) | E201: =IF(A201="","",SUMIFS(采购记录!$D$2:$D$500,采购记录!$B$2:$B$500,A201,采购记录!$C$2:$C$500,B201)) | F201: =IF(A201="","",SUMIFS(订单登记!$F$2:$F$500,订单登记!$D$2:$D$500,A201,订单登记!$E$2:$E$500,B201)) | G201: =IF(A201="","",N(D201)+E201-F201) | H201: =IF(A201="","",商品目录!I201) | I201: =IF(A201="","",IF(ISNUMBER(H201),IF(G201<H201,"该补货",""),""))

Sheet 月度汇总
A1: 中山店铺 · 月度汇总
A3: 本月销售额(按回执) | B3: =SUM(送货回执登记!D2:D500) -> 535 | C3: 以送货回执登记为准,是收入的口径
A4: 本月销售额(按订单,参考) | B4: =SUMIF(订单登记!L2:L500,"<>已取消",订单登记!I2:I500) -> 535 | C4: 与上行差距大说明有单没送或回执没登记
A5: 本月采购额 | B5: =SUM(采购记录!G2:G500) -> 525
A6: 本月已收款 | B6: =SUM(收款记录!C2:C500) -> 100 | C6: 含现结当场收的钱
A7: 当前欠款总额(总应收) | B7: =SUM(应收对账!E2:E151) -> 435 | C7: 这是压在外面的钱,盯紧它
A9: 本月毛利(粗估) | B9: =B3-B5 -> 10 | C9: 销售-采购的粗估口径,没扣库存变化,只作参考
A11: 本月费用(手填):
A12: 油费/车费 | B12: 0 | C12: 手填
A13: 房租(摊到本月) | B13: 0 | C13: 手填
A14: 人工工资 | B14: 0 | C14: 手填
A15: 其他费用 | B15: 0 | C15: 手填
A16: 费用合计 | B16: =SUM(B12:B15) -> 0
A18: 本月净利(粗估) | B18: =B9-B16 -> 10 | C18: 毛利-费用,月底看这个数
